[
  {
    "columnField": "MTBH",
    "columnName": "码头编号",
    "columnType": "string"
  },
  {
    "columnField": "MTMC",
    "columnName": "码头名称",
    "columnType": "string",
    "required": true
  },
  {
    "columnField": "MTDZ",
    "columnName": "码头地址",
    "columnType": "string",
    "required": true
  },
  {
    "columnField": "KYZT",
    "columnName": "可用状态",
    "columnType": "status",
    "required": true
  },
  {
    "columnField": "JD",
    "columnName": "经度",
    "columnType": "double",
    "required": true
  },
  {
    "columnField": "WD",
    "columnName": "纬度",
    "columnType": "double",
    "required": true
  },
  {
    "columnField": "SZDXFJG",
    "columnName": "消防机构",
    "columnType": "department",
    "required": true
  },
  {
    "columnField": "SZDXZQH",
    "columnName": "行政区划",
    "columnType": "region",
    "required": true
  },
  {
    "columnField": "XJZT",
    "columnName": "巡检状态",
    "columnType": "xjzt"
  },
  {
    "columnField": "JCRQ",
    "columnName": "建成日期",
    "columnType": "date",
    "dateFormat": "yyyy-MM-dd"
  },
  {
    "columnField": "SSLD",
    "columnName": "所属路段",
    "columnType": "string"
  },
  {
    "columnField": "QSXS",
    "columnName": "取水形式",
    "columnType": "string"
  },
  {
    "columnField": "QSGD",
    "columnName": "取水高度",
    "columnType": "double"
  },
  {
    "columnField": "SYBGC",
    "columnName": "水源标高差",
    "columnType": "double"
  },
  {
    "columnField": "TCWZ",
    "columnName": "停车位置",
    "columnType": "string"
  },
  {
    "columnField": "TCSL",
    "columnName": "停车数量",
    "columnType": "integer"
  }
]